{"sections":{"main":{"type":"main-customers-login","disabled":true,"settings":{}},"165460479522332vv3":{"type":"otp-login","settings":{"image_enabled":false,"image":"shopify:\/\/shop_images\/800X600_9_d5d2a7c3-4d60-4299-9e4f-53e99ed3f137.jpg","btn_bg_color":"#0d5ea8","btn_text_color":"#ffffff","phone_enable":true,"email_enable":true,"whatsapp_enable":true,"login_title":"Login with OTP","login_sub_title":"Please login to access your saved sizes if you’ve shopped Online or In Store with us.","phone_placeholder":"Phone number","email_placeholder":"Email id","whatsapp_placeholder":"Whatsapp number","otp_title":"Enter OTP","sms_offer_enable":true,"email_offer_enable":true,"whatsapp_offer_enable":true,"account_title":"Account Details","marketing_text":"keep me updated on new updates, exclusive offers, periodical blogs, and everything else on."}},"fdbd4cf6-4193-4558-b10c-0e398f261323":{"type":"otp-login","disabled":true,"settings":{"image_enabled":true,"btn_bg_color":"#1E418E","btn_text_color":"#ffffff","phone_enable":true,"email_enable":true,"whatsapp_enable":true,"login_title":"Login with OTP","login_sub_title":"Enter your log in Credentials","phone_placeholder":"Phone number","email_placeholder":"Email id","whatsapp_placeholder":"Whatsapp number","otp_title":"Enter OTP","sms_offer_enable":true,"email_offer_enable":true,"whatsapp_offer_enable":true,"account_title":"Account Details","marketing_text":"keep me updated on new updates, exclusive offers, periodical blogs, and everything else on."}}},"order":["main","165460479522332vv3","fdbd4cf6-4193-4558-b10c-0e398f261323"]}